<?xml version="1.0" encoding="UTF-8"?>
<odoo>
    <data>
        <template id="assets_frontend" name="top_scroller_icon assets"
            inherit_id="web.assets_frontend">
            <xpath expr="." position="inside">
                <script type="text/javascript"
                    src="/smart_page_scroller/static/src/js/top_scroller.js"></script>
                <link rel="stylesheet" href="/smart_page_scroller/static/src/css/top_button.css"/>
            </xpath>
        </template>
    </data>
</odoo>